didfile.py
didfile-1.0.3.dist-info/METADATA
didfile-1.0.3.dist-info/RECORD
didfile-1.0.3.dist-info/WHEEL
didfile-1.0.3.dist-info/entry_points.txt
didfile-1.0.3.dist-info/top_level.txt
