Metadata-Version: 2.1
Name: didfile
Version: 1.0.3
Summary: Log the things you've done
Home-page: https://github.com/Ovelny/didfile
Author: Ovelny
Author-email: this.is.ovelny@gmail.com
License: MIT
Platform: UNKNOWN
Classifier: License :: OSI Approved :: MIT License
Classifier: Environment :: Console
Classifier: Programming Language :: Python :: 3
Requires-Python: >=3
